extendedio/__init__.py
extendedio/binary_stream.py
ExtendedIO-1.0.0.dist-info/LICENSE
ExtendedIO-1.0.0.dist-info/METADATA
ExtendedIO-1.0.0.dist-info/WHEEL
ExtendedIO-1.0.0.dist-info/top_level.txt
ExtendedIO-1.0.0.dist-info/RECORD
